hello.py
haxall-0.1.1.dist-info/licenses/LICENSE
haxall-0.1.1.dist-info/METADATA
haxall-0.1.1.dist-info/WHEEL
haxall-0.1.1.dist-info/top_level.txt
haxall-0.1.1.dist-info/RECORD
