Metadata-Version: 2.4
Name: haxall
Version: 0.1.1
Summary: Open source software framework for the Internet of Things
License-Expression: AFL-3.0
Requires-Python: >=3.14
License-File: LICENSE
Dynamic: license-file
